Metadata-Version: 2.1
Name: tm-thus
Version: 0.0.19
Summary: A cli tool for use with Trend Micro products.
Home-page: https://github.com/trendmicro/thus
Author: Brendan Johnson
Author-email: brendan_johnson@trendmicro.com
License: UNKNOWN
Platform: UNKNOWN
Classifier: Intended Audience :: Developers
Classifier: Intended Audience :: System Administrators
Classifier: Natural Language :: English
Classifier: License :: OSI Approved :: MIT License
Classifier: Programming Language :: Python
Classifier: Programming Language :: Python :: 3.6
Classifier: Programming Language :: Python :: 3.7
Classifier: Programming Language :: Python :: 3.8
Requires-Python: >=3.6
